{"wikipedia": "https://wikipedia.org/wiki/October_19", "date": "October 19", "deaths": [{"year": "727", "wikipedia": [{"title": "Frithuswith", "wikipedia": "https://wikipedia.org/wiki/Frithuswith"}], "description": "Frithuswith, English saint (b. 650)"}, {"year": "993", "wikipedia": [{"title": "Conrad I of Burgundy", "wikipedia": "https://wikipedia.org/wiki/Conrad_I_of_Burgundy"}], "description": "Conrad I, King of Burgundy (b. c. 925)"}, {"year": "1216", "wikipedia": [{"title": "John, King of England", "wikipedia": "https://wikipedia.org/wiki/John,_King_of_England"}], "description": "John, King of England (b. 1167)"}, {"year": "1287", "wikipedia": [{"title": "Bohemond VII, Count of Tripoli", "wikipedia": "https://wikipedia.org/wiki/Bohemond_VII,_Count_of_Tripoli"}], "description": "Bohemond VII, Count of Tripoli"}, {"year": "1354", "wikipedia": [{"title": "Yusuf I, Sultan of Granada", "wikipedia": "https://wikipedia.org/wiki/Yusuf_I,_Sultan_of_Granada"}], "description": "Yusuf I, Sultan of Granada (b. 1318)"}, {"year": "1432", "wikipedia": [{"title": "John de Mowbray, 2nd Duke of Norfolk", "wikipedia": "https://wikipedia.org/wiki/John_de_Mowbray,_2nd_Duke_of_Norfolk"}, {"title": "Earl Marshal", "wikipedia": "https://wikipedia.org/wiki/Earl_Marshal"}], "description": "John de Mowbray, 2nd Duke of Norfolk, English politician, Earl Marshal of England (b. 1392)"}, {"year": "1587", "wikipedia": [{"title": "Francesco I de' Medici, Grand Duke of Tuscany", "wikipedia": "https://wikipedia.org/wiki/Francesco_I_de%27_Medici,_Grand_Duke_of_Tuscany"}], "description": "Francesco I de' Medici, Grand Duke of Tuscany (b. 1541)"}, {"year": "1595", "wikipedia": [{"title": "Philip Howard, 20th Earl of Arundel", "wikipedia": "https://wikipedia.org/wiki/Philip_Howard,_20th_Earl_of_Arundel"}], "description": "Philip Howard, 20th Earl of Arundel, English nobleman (b. 1537)"}, {"year": "1608", "wikipedia": [{"title": "Martin Delrio", "wikipedia": "https://wikipedia.org/wiki/Martin_Delrio"}], "description": "Martin Delrio, Flemish theologian and author (b. 1551)"}, {"year": "1609", "wikipedia": [{"title": "Jacobus Arminius", "wikipedia": "https://wikipedia.org/wiki/Jacobus_Arminius"}], "description": "Jacobus Arminius, Dutch Reformed theologian (b. 1560)"}, {"year": "1619", "wikipedia": [{"title": "Fujiwara Seika", "wikipedia": "https://wikipedia.org/wiki/Fujiwara_Seika"}], "description": "Fujiwara Seika, Japanese philosopher and educator (b. 1561)"}, {"year": "1636", "wikipedia": [{"title": "Marcin Kazanowski", "wikipedia": "https://wikipedia.org/wiki/Marcin_Kazanowski"}], "description": "Marcin Kazanowski, Polish politician (b. 1566)"}, {"year": "1678", "wikipedia": [{"title": "Samuel Dirksz van Hoogstraten", "wikipedia": "https://wikipedia.org/wiki/Samuel_Dirksz_van_Hoogstraten"}], "description": "Samuel Dirksz van Hoogstraten, Dutch painter (b. 1627)"}, {"year": "1682", "wikipedia": [{"title": "Thomas Browne", "wikipedia": "https://wikipedia.org/wiki/Thomas_Browne"}], "description": "Thomas Browne, English physician and author (b. 1605)"}, {"year": "1723", "wikipedia": [{"title": "Godfrey Kneller", "wikipedia": "https://wikipedia.org/wiki/Godfrey_Kneller"}], "description": "Godfrey Kneller, German-English painter (b. 1646)"}, {"year": "1745", "wikipedia": [{"title": "Jonathan Swift", "wikipedia": "https://wikipedia.org/wiki/Jonathan_Swift"}], "description": "Jonathan Swift, Irish satirist and essayist (b. 1667)"}, {"year": "1772", "wikipedia": [{"title": "Andrea Belli", "wikipedia": "https://wikipedia.org/wiki/Andrea_Belli"}], "description": "Andrea Belli, Maltese architect and businessman (b. 1703)"}, {"year": "1790", "wikipedia": [{"title": "Lyman Hall", "wikipedia": "https://wikipedia.org/wiki/Lyman_Hall"}, {"title": "Governor of Georgia", "wikipedia": "https://wikipedia.org/wiki/Governor_of_Georgia"}], "description": "Lyman Hall, American physician and politician, 16th Governor of Georgia (b. 1724)"}, {"year": "1796", "wikipedia": [{"title": "Michel de Beaupuy", "wikipedia": "https://wikipedia.org/wiki/Michel_de_Beaupuy"}], "description": "Michel de Beaupuy, French general (b. 1755)"}, {"year": "1813", "wikipedia": [{"title": "J\u00f3zef Poniatowski", "wikipedia": "https://wikipedia.org/wiki/J%C3%B3zef_Poniatowski"}], "description": "J\u00f3zef Poniatowski, Polish general (b. 1763)"}, {"year": "1815", "wikipedia": [{"title": "Paolo Mascagni", "wikipedia": "https://wikipedia.org/wiki/Paolo_Mascagni"}], "description": "Paolo Mascagni, Italian physician and anatomist (b. 1755)"}, {"year": "1842", "wikipedia": [{"title": "Aleksey Koltsov", "wikipedia": "https://wikipedia.org/wiki/Aleksey_Koltsov"}], "description": "Aleksey Koltsov, Russian poet and author (b. 1808)"}, {"year": "1851", "wikipedia": [{"title": "Marie Th\u00e9r\u00e8se of France", "wikipedia": "https://wikipedia.org/wiki/Marie_Th%C3%A9r%C3%A8se_of_France"}], "description": "Marie Th\u00e9r\u00e8se of France (b. 1778)"}, {"year": "1856", "wikipedia": [{"title": "William Sprague III", "wikipedia": "https://wikipedia.org/wiki/William_Sprague_III"}, {"title": "Governor of Rhode Island", "wikipedia": "https://wikipedia.org/wiki/Governor_of_Rhode_Island"}], "description": "William Sprague III, American businessman and politician, 14th Governor of Rhode Island (b. 1799)"}, {"year": "1889", "wikipedia": [{"title": "Lu\u00eds I of Portugal", "wikipedia": "https://wikipedia.org/wiki/Lu%C3%ADs_I_of_Portugal"}], "description": "Lu\u00eds I of Portugal (b. 1838)"}, {"year": "1893", "wikipedia": [{"title": "Lucy Stone", "wikipedia": "https://wikipedia.org/wiki/Lucy_Stone"}], "description": "Lucy Stone, American activist (b. 1818)"}, {"year": "1897", "wikipedia": [{"title": "George Pullman", "wikipedia": "https://wikipedia.org/wiki/George_Pullman"}, {"title": "Pullman Company", "wikipedia": "https://wikipedia.org/wiki/Pullman_Company"}], "description": "George Pullman, American engineer and businessman, founded the Pullman Company (b. 1831)"}, {"year": "1901", "wikipedia": [{"title": "Carl Frederik Tietgen", "wikipedia": "https://wikipedia.org/wiki/Carl_Frederik_Tietgen"}, {"title": "GN Store Nord", "wikipedia": "https://wikipedia.org/wiki/GN_Store_Nord"}], "description": "Carl Frederik Tietgen, Danish businessman and philanthropist, founded GN Store Nord (b. 1829)"}, {"year": "1916", "wikipedia": [{"title": "Ioannis Frangoudis", "wikipedia": "https://wikipedia.org/wiki/Ioannis_Frangoudis"}], "description": "Ioannis Frangoudis, Greek general and target shooter (b. 1863)"}, {"year": "1918", "wikipedia": [{"title": "Harold Lockwood", "wikipedia": "https://wikipedia.org/wiki/Harold_Lockwood"}], "description": "Harold Lockwood, American actor (b. 1887)"}, {"year": "1924", "wikipedia": [{"title": "Louis Zborowski", "wikipedia": "https://wikipedia.org/wiki/Louis_Zborowski"}], "description": "Louis Zborowski, English race car driver and engineer (b. 1895)"}, {"year": "1936", "wikipedia": [{"title": "Lu Xun", "wikipedia": "https://wikipedia.org/wiki/Lu_Xun"}], "description": "Lu Xun, Chinese author and critic (b. 1881)"}, {"year": "1937", "wikipedia": [{"title": "Ernest Rutherford", "wikipedia": "https://wikipedia.org/wiki/Ernest_Rutherford"}, {"title": "Nobel Prize in Chemistry", "wikipedia": "https://wikipedia.org/wiki/Nobel_Prize_in_Chemistry"}], "description": "Ernest Rutherford, New Zealand-English physicist and chemist, Nobel Prize laureate (b. 1871)"}, {"year": "1943", "wikipedia": [{"title": "Camille Claudel", "wikipedia": "https://wikipedia.org/wiki/Camille_Claudel"}], "description": "Camille Claudel, French sculptor and illustrator (b. 1864)"}, {"year": "1944", "wikipedia": [{"title": "D\u00e9nes K\u0151nig", "wikipedia": "https://wikipedia.org/wiki/D%C3%A9nes_K%C5%91nig"}], "description": "D\u00e9nes K\u0151nig, Hungarian mathematician (b. 1884)"}, {"year": "1945", "wikipedia": [{"title": "Plutarco El\u00edas Calles", "wikipedia": "https://wikipedia.org/wiki/Plutarco_El%C3%ADas_Calles"}, {"title": "President of Mexico", "wikipedia": "https://wikipedia.org/wiki/President_of_Mexico"}], "description": "Plutarco El\u00edas Calles, Mexican general and politician, 40th President of Mexico (b. 1877)"}, {"year": "1945", "wikipedia": [{"title": "N. C. Wyeth", "wikipedia": "https://wikipedia.org/wiki/N._C._Wyeth"}], "description": "N. C. Wyeth, American painter and illustrator (b. 1882)"}, {"year": "1950", "wikipedia": [{"title": "Edna St. Vincent Millay", "wikipedia": "https://wikipedia.org/wiki/Edna_St._Vincent_Millay"}], "description": "Edna St. Vincent Millay, American poet and playwright (b. 1892)"}, {"year": "1952", "wikipedia": [{"title": "Edward S. Curtis", "wikipedia": "https://wikipedia.org/wiki/Edward_S._Curtis"}], "description": "Edward S. Curtis, American ethnologist and photographer (b. 1868)"}, {"year": "1956", "wikipedia": [{"title": "Isham Jones", "wikipedia": "https://wikipedia.org/wiki/Isham_Jones"}], "description": "Isham Jones, American saxophonist, songwriter, and bandleader (b. 1894)"}, {"year": "1960", "wikipedia": [{"title": "George Wallace (Australian comedian)", "wikipedia": "https://wikipedia.org/wiki/George_Wallace_(Australian_comedian)"}], "description": "George Wallace, Australian comedian, actor, and screenwriter (b. 1895)"}, {"year": "1961", "wikipedia": [{"title": "\u015eemsettin G\u00fcnaltay", "wikipedia": "https://wikipedia.org/wiki/%C5%9Eemsettin_G%C3%BCnaltay"}, {"title": "List of Prime Ministers of Turkey", "wikipedia": "https://wikipedia.org/wiki/List_of_Prime_Ministers_of_Turkey"}], "description": "\u015eemsettin G\u00fcnaltay, Turkish historian and politician, 9th Prime Minister of Turkey (b. 1883)"}, {"year": "1964", "wikipedia": [{"title": "Sergey Biryuzov", "wikipedia": "https://wikipedia.org/wiki/Sergey_Biryuzov"}, {"title": "Marshal of the Soviet Union", "wikipedia": "https://wikipedia.org/wiki/Marshal_of_the_Soviet_Union"}], "description": "Sergey Biryuzov, Marshal of the Soviet Union (b. 1904)"}, {"year": "1964", "wikipedia": [{"title": "Nettie Palmer", "wikipedia": "https://wikipedia.org/wiki/Nettie_Palmer"}], "description": "Nettie Palmer, Australian poet and critic (b. 1885)"}, {"year": "1964", "wikipedia": [{"title": "Christopher Vane, 10th Baron Barnard", "wikipedia": "https://wikipedia.org/wiki/Christopher_Vane,_10th_Baron_Barnard"}, {"title": "Lord Lieutenant of Durham", "wikipedia": "https://wikipedia.org/wiki/Lord_Lieutenant_of_Durham"}], "description": "Christopher Vane, 10th Baron Barnard, English soldier and politician, Lord Lieutenant of Durham (b. 1888)"}, {"year": "1965", "wikipedia": [{"title": "Edward Willis Redfield", "wikipedia": "https://wikipedia.org/wiki/Edward_Willis_Redfield"}], "description": "Edward Willis Redfield, American painter and educator (b. 1869)"}, {"year": "1969", "wikipedia": [{"title": "Lacey Hearn", "wikipedia": "https://wikipedia.org/wiki/Lacey_Hearn"}], "description": "Lacey Hearn, American sprinter (b. 1881)"}, {"year": "1970", "wikipedia": [{"title": "L\u00e1zaro C\u00e1rdenas", "wikipedia": "https://wikipedia.org/wiki/L%C3%A1zaro_C%C3%A1rdenas"}, {"title": "President of Mexico", "wikipedia": "https://wikipedia.org/wiki/President_of_Mexico"}], "description": "L\u00e1zaro C\u00e1rdenas, Mexican general and politician, 44th President of Mexico (b. 1895)"}, {"year": "1978", "wikipedia": [{"title": "Gig Young", "wikipedia": "https://wikipedia.org/wiki/Gig_Young"}], "description": "Gig Young, American actor (b. 1913)"}, {"year": "1983", "wikipedia": [{"title": "Maurice Bishop", "wikipedia": "https://wikipedia.org/wiki/Maurice_Bishop"}, {"title": "Prime Minister of Grenada", "wikipedia": "https://wikipedia.org/wiki/Prime_Minister_of_Grenada"}], "description": "Maurice Bishop, Aruban-Grenadian lawyer and politician, 2nd Prime Minister of Grenada (b. 1944)"}, {"year": "1984", "wikipedia": [{"title": "Jerzy Popie\u0142uszko", "wikipedia": "https://wikipedia.org/wiki/Jerzy_Popie%C5%82uszko"}], "description": "Jerzy Popie\u0142uszko, Polish priest and activist (b. 1947)"}, {"year": "1985", "wikipedia": [{"title": "Alfred Rouleau", "wikipedia": "https://wikipedia.org/wiki/Alfred_Rouleau"}], "description": "Alfred Rouleau, Canadian businessman (b. 1915)"}, {"year": "1986", "wikipedia": [{"title": "Dele Giwa", "wikipedia": "https://wikipedia.org/wiki/Dele_Giwa"}, {"title": "Newswatch (Nigeria)", "wikipedia": "https://wikipedia.org/wiki/Newswatch_(Nigeria)"}], "description": "Dele Giwa, Nigerian journalist, co-founded Newswatch Magazine (b. 1947)"}, {"year": "1986", "wikipedia": [{"title": "Samora Machel", "wikipedia": "https://wikipedia.org/wiki/Samora_Machel"}, {"title": "President of Mozambique", "wikipedia": "https://wikipedia.org/wiki/President_of_Mozambique"}], "description": "Samora Machel, Mozambican commander and politician, 1st President of Mozambique (b. 1933)"}, {"year": "1987", "wikipedia": [{"title": "Jacqueline du Pr\u00e9", "wikipedia": "https://wikipedia.org/wiki/Jacqueline_du_Pr%C3%A9"}], "description": "Jacqueline du Pr\u00e9, English cellist and educator (b. 1945)"}, {"year": "1987", "wikipedia": [{"title": "Hermann Lang", "wikipedia": "https://wikipedia.org/wiki/Hermann_Lang"}], "description": "Hermann Lang, German race car driver (b. 1909)"}, {"year": "1988", "wikipedia": [{"title": "Son House", "wikipedia": "https://wikipedia.org/wiki/Son_House"}], "description": "Son House, American singer and guitarist (b. 1902)"}, {"year": "1992", "wikipedia": [{"title": "Magnus Pyke", "wikipedia": "https://wikipedia.org/wiki/Magnus_Pyke"}], "description": "Magnus Pyke, English scientist and television host (b. 1908)"}, {"year": "1994", "wikipedia": [{"title": "Martha Raye", "wikipedia": "https://wikipedia.org/wiki/Martha_Raye"}], "description": "Martha Raye, American actress and comedian (b. 1916)"}, {"year": "1995", "wikipedia": [{"title": "Don Cherry (trumpeter)", "wikipedia": "https://wikipedia.org/wiki/Don_Cherry_(trumpeter)"}], "description": "Don Cherry, American trumpet player (b. 1936)"}, {"year": "1995", "wikipedia": [{"title": "Harilaos Perpessas", "wikipedia": "https://wikipedia.org/wiki/Harilaos_Perpessas"}], "description": "Harilaos Perpessas, Greek pianist and composer (b. 1907)"}, {"year": "1997", "wikipedia": [{"title": "Glen Buxton", "wikipedia": "https://wikipedia.org/wiki/Glen_Buxton"}], "description": "Glen Buxton, American guitarist and songwriter (b. 1947)"}, {"year": "1997", "wikipedia": [{"title": "Ken Wood (manufacturer)", "wikipedia": "https://wikipedia.org/wiki/Ken_Wood_(manufacturer)"}], "description": "Ken Wood, English businessman (b. 1916)"}, {"year": "1999", "wikipedia": [{"title": "James C. Murray", "wikipedia": "https://wikipedia.org/wiki/James_C._Murray"}], "description": "James C. Murray, American soldier, lawyer, and politician (b. 1917)"}, {"year": "1999", "wikipedia": [{"title": "Nathalie Sarraute", "wikipedia": "https://wikipedia.org/wiki/Nathalie_Sarraute"}], "description": "Nathalie Sarraute, Russian-French lawyer and author (b. 1900)"}, {"year": "2002", "wikipedia": [{"title": "Nikolay Rukavishnikov", "wikipedia": "https://wikipedia.org/wiki/Nikolay_Rukavishnikov"}], "description": "Nikolay Rukavishnikov, Russian physicist and astronaut (b. 1932)"}, {"year": "2003", "wikipedia": [{"title": "Road Warrior Hawk", "wikipedia": "https://wikipedia.org/wiki/Road_Warrior_Hawk"}], "description": "Road Warrior Hawk, American wrestler (b. 1957)"}, {"year": "2003", "wikipedia": [{"title": "Alija Izetbegovi\u0107", "wikipedia": "https://wikipedia.org/wiki/Alija_Izetbegovi%C4%87"}, {"title": "President of Bosnia and Herzegovina", "wikipedia": "https://wikipedia.org/wiki/President_of_Bosnia_and_Herzegovina"}], "description": "Alija Izetbegovi\u0107, Bosniak lawyer and politician, 1st President of Bosnia and Herzegovina (b. 1925)"}, {"year": "2003", "wikipedia": [{"title": "Margaret Murie", "wikipedia": "https://wikipedia.org/wiki/Margaret_Murie"}], "description": "Margaret Murie, American environmentalist and author (b. 1902)"}, {"year": "2003", "wikipedia": [{"title": "Nello Pagani", "wikipedia": "https://wikipedia.org/wiki/Nello_Pagani"}], "description": "Nello Pagani, Italian motorcycle racer and race car driver (b. 1911)"}, {"year": "2005", "wikipedia": [{"title": "Ryan Dallas Cook", "wikipedia": "https://wikipedia.org/wiki/Ryan_Dallas_Cook"}], "description": "Ryan Dallas Cook, American trombonist (b. 1982)"}, {"year": "2006", "wikipedia": [{"title": "James Glennon", "wikipedia": "https://wikipedia.org/wiki/James_Glennon"}], "description": "James Glennon, American cinematographer (b. 1942)"}, {"year": "2006", "wikipedia": [{"title": "Phyllis Kirk", "wikipedia": "https://wikipedia.org/wiki/Phyllis_Kirk"}], "description": "Phyllis Kirk, American actress (b. 1927)"}, {"year": "2007", "wikipedia": [{"title": "Winifred Asprey", "wikipedia": "https://wikipedia.org/wiki/Winifred_Asprey"}], "description": "Winifred Asprey, American mathematician and computer scientist (b. 1917)"}, {"year": "2007", "wikipedia": [{"title": "Randall Forsberg", "wikipedia": "https://wikipedia.org/wiki/Randall_Forsberg"}], "description": "Randall Forsberg, American activist and author (b. 1943)"}, {"year": "2007", "wikipedia": [{"title": "Michael Maidens", "wikipedia": "https://wikipedia.org/wiki/Michael_Maidens"}], "description": "Michael Maidens, English footballer (b. 1987)"}, {"year": "2007", "wikipedia": [{"title": "Jan Wolkers", "wikipedia": "https://wikipedia.org/wiki/Jan_Wolkers"}], "description": "Jan Wolkers, Dutch author, sculptor, and painter (b. 1925)"}, {"year": "2008", "wikipedia": [{"title": "Richard Blackwell", "wikipedia": "https://wikipedia.org/wiki/Richard_Blackwell"}], "description": "Richard Blackwell, American actor, fashion designer, and critic (b. 1922)"}, {"year": "2009", "wikipedia": [{"title": "Howard Unruh", "wikipedia": "https://wikipedia.org/wiki/Howard_Unruh"}], "description": "Howard Unruh, American murderer (b. 1921)"}, {"year": "2009", "wikipedia": [{"title": "Joseph Wiseman", "wikipedia": "https://wikipedia.org/wiki/Joseph_Wiseman"}], "description": "Joseph Wiseman, Canadian-American actor (b. 1918)"}, {"year": "2010", "wikipedia": [{"title": "Tom Bosley", "wikipedia": "https://wikipedia.org/wiki/Tom_Bosley"}], "description": "Tom Bosley, American actor (b. 1927)"}, {"year": "2011", "wikipedia": [{"title": "Kakkanadan", "wikipedia": "https://wikipedia.org/wiki/Kakkanadan"}], "description": "Kakkanadan, Indian author (b. 1935)"}, {"year": "2012", "wikipedia": [{"title": "Lincoln Alexander", "wikipedia": "https://wikipedia.org/wiki/Lincoln_Alexander"}, {"title": "Lieutenant Governor of Ontario", "wikipedia": "https://wikipedia.org/wiki/Lieutenant_Governor_of_Ontario"}], "description": "Lincoln Alexander, Canadian lawyer and politician, 24th Lieutenant Governor of Ontario (b. 1922)"}, {"year": "2012", "wikipedia": [{"title": "Wissam al-Hassan", "wikipedia": "https://wikipedia.org/wiki/Wissam_al-Hassan"}], "description": "Wissam al-Hassan, Lebanese general (b. 1965)"}, {"year": "2012", "wikipedia": [{"title": "Wiyogo Atmodarminto", "wikipedia": "https://wikipedia.org/wiki/Wiyogo_Atmodarminto"}, {"title": "Governor of Jakarta", "wikipedia": "https://wikipedia.org/wiki/Governor_of_Jakarta"}], "description": "Wiyogo Atmodarminto, Indonesian general and politician, 10th Governor of Jakarta (b. 1922)"}, {"year": "2012", "wikipedia": [{"title": "Mike Graham (wrestler)", "wikipedia": "https://wikipedia.org/wiki/Mike_Graham_(wrestler)"}], "description": "Mike Graham, American wrestler (b. 1951)"}, {"year": "2012", "wikipedia": [{"title": "Fiorenzo Magni", "wikipedia": "https://wikipedia.org/wiki/Fiorenzo_Magni"}], "description": "Fiorenzo Magni, Italian cyclist (b. 1920)"}, {"year": "2013", "wikipedia": [{"title": "John Bergamo", "wikipedia": "https://wikipedia.org/wiki/John_Bergamo"}], "description": "John Bergamo, American drummer and composer (b. 1940)"}, {"year": "2013", "wikipedia": [{"title": "Noel Harrison", "wikipedia": "https://wikipedia.org/wiki/Noel_Harrison"}], "description": "Noel Harrison, English singer, actor, and skier (b. 1934)"}, {"year": "2013", "wikipedia": [{"title": "Ronald Shannon Jackson", "wikipedia": "https://wikipedia.org/wiki/Ronald_Shannon_Jackson"}], "description": "Ronald Shannon Jackson, American drummer and composer (b. 1940)"}, {"year": "2013", "wikipedia": [{"title": "Mikihiko Renj\u014d", "wikipedia": "https://wikipedia.org/wiki/Mikihiko_Renj%C5%8D"}], "description": "Mikihiko Renj\u014d, Japanese author (b. 1948)"}, {"year": "2013", "wikipedia": [{"title": "Mahmoud Zoufonoun", "wikipedia": "https://wikipedia.org/wiki/Mahmoud_Zoufonoun"}], "description": "Mahmoud Zoufonoun, Iranian-American violinist and composer (b. 1920)"}, {"year": "2014", "wikipedia": [{"title": "John Holt (singer)", "wikipedia": "https://wikipedia.org/wiki/John_Holt_(singer)"}], "description": "John Holt, Jamaican singer-songwriter (b. 1947)"}, {"year": "2014", "wikipedia": [{"title": "Stephen Paulus", "wikipedia": "https://wikipedia.org/wiki/Stephen_Paulus"}], "description": "Stephen Paulus, American composer (b. 1949)"}, {"year": "2014", "wikipedia": [{"title": "Raphael Ravenscroft", "wikipedia": "https://wikipedia.org/wiki/Raphael_Ravenscroft"}], "description": "Raphael Ravenscroft, English saxophonist and composer (b. 1954)"}, {"year": "2014", "wikipedia": [{"title": "Serena Shim", "wikipedia": "https://wikipedia.org/wiki/Serena_Shim"}], "description": "Serena Shim, Lebanese-American journalist (b. 1984)"}, {"year": "2015", "wikipedia": [{"title": "Leon Bramlett", "wikipedia": "https://wikipedia.org/wiki/Leon_Bramlett"}], "description": "Leon Bramlett, American football player and politician (b. 1923)"}, {"year": "2015", "wikipedia": [{"title": "Bill Daley (American football)", "wikipedia": "https://wikipedia.org/wiki/Bill_Daley_(American_football)"}], "description": "Bill Daley, American football player and sportscaster (b. 1919)"}, {"year": "2015", "wikipedia": [{"title": "Fleming Mackell", "wikipedia": "https://wikipedia.org/wiki/Fleming_Mackell"}], "description": "Fleming Mackell, Canadian ice hockey player and singer (b. 1929)"}, {"year": "2015", "wikipedia": [{"title": "Ali Treki", "wikipedia": "https://wikipedia.org/wiki/Ali_Treki"}, {"title": "Minister of Foreign Affairs (Libya)", "wikipedia": "https://wikipedia.org/wiki/Minister_of_Foreign_Affairs_(Libya)"}], "description": "Ali Treki, Libyan politician and diplomat, Libyan Minister of Foreign Affairs (b. 1938)"}, {"year": "2016", "wikipedia": [{"title": "Phil Chess", "wikipedia": "https://wikipedia.org/wiki/Phil_Chess"}, {"title": "Chess Records", "wikipedia": "https://wikipedia.org/wiki/Chess_Records"}], "description": "Phil Chess, Czech-American record producer, co-founded Chess Records (b. 1921)"}, {"year": "2016", "wikipedia": [{"title": "Giovanni Steff\u00e8", "wikipedia": "https://wikipedia.org/wiki/Giovanni_Steff%C3%A8"}], "description": "Giovanni Steff\u00e8, Italian rower (b. 1928)"}]}