{"wikipedia": "https://wikipedia.org/wiki/July_10", "date": "July 10", "deaths": [{"year": "138", "wikipedia": [{"title": "Hadrian", "wikipedia": "https://wikipedia.org/wiki/Hadrian"}], "description": "Hadrian, Roman emperor (b. 76)"}, {"year": "645", "wikipedia": [{"title": "Soga no Iruka", "wikipedia": "https://wikipedia.org/wiki/Soga_no_Iruka"}], "description": "Soga no Iruka, Japanese politician"}, {"year": "649", "wikipedia": [{"title": "Emperor Taizong of Tang", "wikipedia": "https://wikipedia.org/wiki/Emperor_Taizong_of_Tang"}], "description": "Emperor Taizong of Tang (b. 598)"}, {"year": "831", "wikipedia": [{"title": "Zubaidah bint Ja`far", "wikipedia": "https://wikipedia.org/wiki/Zubaidah_bint_Ja%60far"}], "description": "Zubaidah bint Ja`far, Abbasid Princess"}, {"year": "1086", "wikipedia": [{"title": "Canute IV of Denmark", "wikipedia": "https://wikipedia.org/wiki/Canute_IV_of_Denmark"}], "description": "King Canute IV of Denmark (b. 1043)"}, {"year": "1103", "wikipedia": [{"title": "Eric I of Denmark", "wikipedia": "https://wikipedia.org/wiki/Eric_I_of_Denmark"}], "description": "Eric I of Denmark (b. 1060)"}, {"year": "1290", "wikipedia": [{"title": "Ladislaus IV of Hungary", "wikipedia": "https://wikipedia.org/wiki/Ladislaus_IV_of_Hungary"}], "description": "Ladislaus IV of Hungary (b. 1262)"}, {"year": "1460", "wikipedia": [{"title": "Humphrey Stafford, 1st Duke of Buckingham", "wikipedia": "https://wikipedia.org/wiki/Humphrey_Stafford,_1st_Duke_of_Buckingham"}, {"title": "Lord High Constable of England", "wikipedia": "https://wikipedia.org/wiki/Lord_High_Constable_of_England"}], "description": "Humphrey Stafford, 1st Duke of Buckingham, English commander and politician, Lord High Constable of England (b. 1402)"}, {"year": "1460", "wikipedia": [{"title": "John Talbot, 2nd Earl of Shrewsbury", "wikipedia": "https://wikipedia.org/wiki/John_Talbot,_2nd_Earl_of_Shrewsbury"}], "description": "John Talbot, 2nd Earl of Shrewsbury (b. c. 1413)"}, {"year": "1461", "wikipedia": [{"title": "Stephen Thomas of Bosnia", "wikipedia": "https://wikipedia.org/wiki/Stephen_Thomas_of_Bosnia"}], "description": "Stephen Thomas of Bosnia (b. 1412)"}, {"year": "1473", "wikipedia": [{"title": "James II of Cyprus", "wikipedia": "https://wikipedia.org/wiki/James_II_of_Cyprus"}], "description": "James II of Cyprus (b. c. 1440)"}, {"year": "1480", "wikipedia": [{"title": "Ren\u00e9 of Anjou", "wikipedia": "https://wikipedia.org/wiki/Ren%C3%A9_of_Anjou"}], "description": "Ren\u00e9 of Anjou (b. 1410)"}, {"year": "1510", "wikipedia": [{"title": "Catherine Cornaro", "wikipedia": "https://wikipedia.org/wiki/Catherine_Cornaro"}], "description": "Catherine Cornaro, Queen of Cyprus (b. 1454)"}, {"year": "1559", "wikipedia": [{"title": "Henry II of France", "wikipedia": "https://wikipedia.org/wiki/Henry_II_of_France"}], "description": "Henry II of France (b. 1519)"}, {"year": "1584", "wikipedia": [{"title": "William I of Orange", "wikipedia": "https://wikipedia.org/wiki/William_I_of_Orange"}], "description": "William I of Orange (b. 1533)"}, {"year": "1590", "wikipedia": [{"title": "Charles II, Archduke of Austria", "wikipedia": "https://wikipedia.org/wiki/Charles_II,_Archduke_of_Austria"}], "description": "Charles II, Archduke of Austria (b. 1540)"}, {"year": "1594", "wikipedia": [{"title": "Paolo Bellasio", "wikipedia": "https://wikipedia.org/wiki/Paolo_Bellasio"}], "description": "Paolo Bellasio, Italian organist and composer (b. 1554)"}, {"year": "1603", "wikipedia": [{"title": "Joan Ter\u00e8s i Borrull", "wikipedia": "https://wikipedia.org/wiki/Joan_Ter%C3%A8s_i_Borrull"}], "description": "Joan Ter\u00e8s i Borrull, Spanish archbishop and academic (b. 1538)"}, {"year": "1621", "wikipedia": [{"title": "Charles Bonaventure de Longueval, Count of Bucquoy", "wikipedia": "https://wikipedia.org/wiki/Charles_Bonaventure_de_Longueval,_Count_of_Bucquoy"}], "description": "Charles Bonaventure de Longueval, Count of Bucquoy, French commander (b. 1571)"}, {"year": "1653", "wikipedia": [{"title": "Gabriel Naud\u00e9", "wikipedia": "https://wikipedia.org/wiki/Gabriel_Naud%C3%A9"}], "description": "Gabriel Naud\u00e9, French librarian and scholar (b. 1600)"}, {"year": "1680", "wikipedia": [{"title": "Louis Mor\u00e9ri", "wikipedia": "https://wikipedia.org/wiki/Louis_Mor%C3%A9ri"}], "description": "Louis Mor\u00e9ri, French priest and scholar (b. 1643)"}, {"year": "1683", "wikipedia": [{"title": "Fran\u00e7ois Eudes de M\u00e9zeray", "wikipedia": "https://wikipedia.org/wiki/Fran%C3%A7ois_Eudes_de_M%C3%A9zeray"}], "description": "Fran\u00e7ois Eudes de M\u00e9zeray, French historian and author (b. 1610)"}, {"year": "1686", "wikipedia": [{"title": "John Fell (bishop)", "wikipedia": "https://wikipedia.org/wiki/John_Fell_(bishop)"}], "description": "John Fell, English bishop and academic (b. 1625)"}, {"year": "1776", "wikipedia": [{"title": "Richard Peters (priest)", "wikipedia": "https://wikipedia.org/wiki/Richard_Peters_(priest)"}], "description": "Richard Peters, English lawyer and minister (b. 1704)"}, {"year": "1794", "wikipedia": [{"title": "Gaspard de Bernard de Marigny", "wikipedia": "https://wikipedia.org/wiki/Gaspard_de_Bernard_de_Marigny"}], "description": "Gaspard de Bernard de Marigny, French general (d. 1754)"}, {"year": "1806", "wikipedia": [{"title": "George Stubbs", "wikipedia": "https://wikipedia.org/wiki/George_Stubbs"}], "description": "George Stubbs, English painter and academic (b. 1724)"}, {"year": "1851", "wikipedia": [{"title": "Louis Daguerre", "wikipedia": "https://wikipedia.org/wiki/Louis_Daguerre"}, {"title": "Daguerreotype", "wikipedia": "https://wikipedia.org/wiki/Daguerreotype"}], "description": "Louis Daguerre, French photographer and physicist, invented the daguerreotype (b. 1787)"}, {"year": "1863", "wikipedia": [{"title": "Clement Clarke Moore", "wikipedia": "https://wikipedia.org/wiki/Clement_Clarke_Moore"}], "description": "Clement Clarke Moore, American author and educator (b. 1779)"}, {"year": "1881", "wikipedia": [{"title": "Georg Hermann Nicolai", "wikipedia": "https://wikipedia.org/wiki/Georg_Hermann_Nicolai"}], "description": "Georg Hermann Nicolai, German architect and academic (b. 1812)"}, {"year": "1884", "wikipedia": [{"title": "Paul Morphy", "wikipedia": "https://wikipedia.org/wiki/Paul_Morphy"}], "description": "Paul Morphy, American chess player (b. 1837)"}, {"year": "1908", "wikipedia": [{"title": "Phoebe Knapp", "wikipedia": "https://wikipedia.org/wiki/Phoebe_Knapp"}], "description": "Phoebe Knapp, American organist and composer (b. 1839)"}, {"year": "1915", "wikipedia": [{"title": "Hendrik Willem Mesdag", "wikipedia": "https://wikipedia.org/wiki/Hendrik_Willem_Mesdag"}], "description": "Hendrik Willem Mesdag, Dutch painter (b. 1831)"}, {"year": "1920", "wikipedia": [{"title": "John Fisher, 1st Baron Fisher", "wikipedia": "https://wikipedia.org/wiki/John_Fisher,_1st_Baron_Fisher"}], "description": "John Fisher, 1st Baron Fisher, British admiral (b. 1841)"}, {"year": "1929", "wikipedia": [{"title": "\u00c8ve Lavalli\u00e8re", "wikipedia": "https://wikipedia.org/wiki/%C3%88ve_Lavalli%C3%A8re"}], "description": "\u00c8ve Lavalli\u00e8re, French actress (b. 1866)"}, {"year": "1941", "wikipedia": [{"title": "Jelly Roll Morton", "wikipedia": "https://wikipedia.org/wiki/Jelly_Roll_Morton"}], "description": "Jelly Roll Morton, American pianist, composer, and bandleader (b. 1890)"}, {"year": "1950", "wikipedia": [{"title": "Richard Maury", "wikipedia": "https://wikipedia.org/wiki/Richard_Maury"}], "description": "Richard Maury, American-Argentinian engineer (b. 1882)"}, {"year": "1952", "wikipedia": [{"title": "Rued Langgaard", "wikipedia": "https://wikipedia.org/wiki/Rued_Langgaard"}], "description": "Rued Langgaard, Danish organist and composer (b. 1893)"}, {"year": "1954", "wikipedia": [{"title": "Calogero Vizzini", "wikipedia": "https://wikipedia.org/wiki/Calogero_Vizzini"}], "description": "Calogero Vizzini, Italian mob boss (b. 1877)"}, {"year": "1956", "wikipedia": [{"title": "Joe Giard", "wikipedia": "https://wikipedia.org/wiki/Joe_Giard"}], "description": "Joe Giard, American baseball player (b. 1898)"}, {"year": "1960", "wikipedia": [{"title": "S\u00e6bj\u00f8rn Buttedahl", "wikipedia": "https://wikipedia.org/wiki/S%C3%A6bj%C3%B8rn_Buttedahl"}], "description": "S\u00e6bj\u00f8rn Buttedahl, Norwegian actor and sculptor (b. 1876)"}, {"year": "1962", "wikipedia": [{"title": "Yehuda Leib Maimon", "wikipedia": "https://wikipedia.org/wiki/Yehuda_Leib_Maimon"}], "description": "Yehuda Leib Maimon, Israeli rabbi and politician (b. 1875)"}, {"year": "1963", "wikipedia": [{"title": "Teddy Wakelam", "wikipedia": "https://wikipedia.org/wiki/Teddy_Wakelam"}], "description": "Teddy Wakelam, English rugby player and sportscaster (b. 1893)"}, {"year": "1970", "wikipedia": [{"title": "Bjarni Benediktsson (born 1908)", "wikipedia": "https://wikipedia.org/wiki/Bjarni_Benediktsson_(born_1908)"}, {"title": "Prime Minister of Iceland", "wikipedia": "https://wikipedia.org/wiki/Prime_Minister_of_Iceland"}], "description": "Bjarni Benediktsson, Icelandic academic and politician, 13th Prime Minister of Iceland (b. 1908)"}, {"year": "1971", "wikipedia": [{"title": "Laurent Dauthuille", "wikipedia": "https://wikipedia.org/wiki/Laurent_Dauthuille"}], "description": "Laurent Dauthuille, French boxer (b. 1924)"}, {"year": "1971", "wikipedia": [{"title": "George Kenner", "wikipedia": "https://wikipedia.org/wiki/George_Kenner"}], "description": "George Kenner, German-American painter and illustrator (b. 1888)"}, {"year": "1972", "wikipedia": [{"title": "Lovie Austin", "wikipedia": "https://wikipedia.org/wiki/Lovie_Austin"}], "description": "Lovie Austin, American pianist, composer, and bandleader (b. 1887)"}, {"year": "1978", "wikipedia": [{"title": "John D. Rockefeller III", "wikipedia": "https://wikipedia.org/wiki/John_D._Rockefeller_III"}, {"title": "Asia Society", "wikipedia": "https://wikipedia.org/wiki/Asia_Society"}], "description": "John D. Rockefeller III, American businessman and philanthropist, founded the Asia Society (b. 1906)"}, {"year": "1979", "wikipedia": [{"title": "Arthur Fiedler", "wikipedia": "https://wikipedia.org/wiki/Arthur_Fiedler"}], "description": "Arthur Fiedler, American conductor (b. 1894)"}, {"year": "1980", "wikipedia": [{"title": "Joseph Krumgold", "wikipedia": "https://wikipedia.org/wiki/Joseph_Krumgold"}], "description": "Joseph Krumgold, American author and screenwriter (b. 1908)"}, {"year": "1985", "wikipedia": [{"title": "Fernando Pereira", "wikipedia": "https://wikipedia.org/wiki/Fernando_Pereira"}], "description": "Fernando Pereira, Dutch photographer (b. 1950)"}, {"year": "1986", "wikipedia": [{"title": "Tadeusz Piotrowski (mountaineer)", "wikipedia": "https://wikipedia.org/wiki/Tadeusz_Piotrowski_(mountaineer)"}], "description": "Tadeusz Piotrowski, Polish mountaineer and author (b. 1940)"}, {"year": "1987", "wikipedia": [{"title": "John Hammond (producer)", "wikipedia": "https://wikipedia.org/wiki/John_Hammond_(producer)"}], "description": "John Hammond, American record producer, critic, and activist (b. 1910)"}, {"year": "1989", "wikipedia": [{"title": "Mel Blanc", "wikipedia": "https://wikipedia.org/wiki/Mel_Blanc"}], "description": "Mel Blanc, American voice actor (b. 1908)"}, {"year": "1993", "wikipedia": [{"title": "Ruth Krauss", "wikipedia": "https://wikipedia.org/wiki/Ruth_Krauss"}], "description": "Ruth Krauss, American author and poet (b. 1901)"}, {"year": "1993", "wikipedia": [{"title": "Sam Rolfe", "wikipedia": "https://wikipedia.org/wiki/Sam_Rolfe"}], "description": "Sam Rolfe, American screenwriter and producer (b. 1924)"}, {"year": "1995", "wikipedia": [{"title": "Mehmet Ali Aybar", "wikipedia": "https://wikipedia.org/wiki/Mehmet_Ali_Aybar"}], "description": "Mehmet Ali Aybar, Turkish lawyer and politician (b. 1908)"}, {"year": "1996", "wikipedia": [{"title": "Eno Raud", "wikipedia": "https://wikipedia.org/wiki/Eno_Raud"}], "description": "Eno Raud, Estonian author (b. 1928)"}, {"year": "2000", "wikipedia": [{"title": "Vakkom Majeed", "wikipedia": "https://wikipedia.org/wiki/Vakkom_Majeed"}], "description": "Vakkom Majeed, Indian journalist and politician (b. 1909)"}, {"year": "2002", "wikipedia": [{"title": "Jean-Pierre C\u00f4t\u00e9", "wikipedia": "https://wikipedia.org/wiki/Jean-Pierre_C%C3%B4t%C3%A9"}, {"title": "Lieutenant Governor of Quebec", "wikipedia": "https://wikipedia.org/wiki/Lieutenant_Governor_of_Quebec"}], "description": "Jean-Pierre C\u00f4t\u00e9, Canadian politician, 23rd Lieutenant Governor of Quebec (b. 1926)"}, {"year": "2002", "wikipedia": [{"title": "Evangelos Florakis", "wikipedia": "https://wikipedia.org/wiki/Evangelos_Florakis"}], "description": "Evangelos Florakis, Greek general (b. 1943)"}, {"year": "2002", "wikipedia": [{"title": "Laurence Janifer", "wikipedia": "https://wikipedia.org/wiki/Laurence_Janifer"}], "description": "Laurence Janifer, American author (b. 1933)"}, {"year": "2003", "wikipedia": [{"title": "Winston Graham", "wikipedia": "https://wikipedia.org/wiki/Winston_Graham"}], "description": "Winston Graham, English author (b. 1908)"}, {"year": "2003", "wikipedia": [{"title": "Hartley Shawcross, Baron Shawcross", "wikipedia": "https://wikipedia.org/wiki/Hartley_Shawcross,_Baron_Shawcross"}, {"title": "Attorney General for England and Wales", "wikipedia": "https://wikipedia.org/wiki/Attorney_General_for_England_and_Wales"}], "description": "Hartley Shawcross, Baron Shawcross, German-English lawyer and politician, Attorney General for England and Wales (b. 1902)"}, {"year": "2004", "wikipedia": [{"title": "Pati Behrs", "wikipedia": "https://wikipedia.org/wiki/Pati_Behrs"}], "description": "Pati Behrs, Russian-American ballerina and actress (b. 1922)"}, {"year": "2005", "wikipedia": [{"title": "A. J. Quinnell", "wikipedia": "https://wikipedia.org/wiki/A._J._Quinnell"}], "description": "A. J. Quinnell, English author (b. 1940)"}, {"year": "2006", "wikipedia": [{"title": "Shamil Basayev", "wikipedia": "https://wikipedia.org/wiki/Shamil_Basayev"}], "description": "Shamil Basayev, Chechen terrorist rebel leader (b. 1965)"}, {"year": "2007", "wikipedia": [{"title": "Doug Marlette", "wikipedia": "https://wikipedia.org/wiki/Doug_Marlette"}], "description": "Doug Marlette, American cartoonist and author (b. 1949)"}, {"year": "2008", "wikipedia": [{"title": "Hiroaki Aoki", "wikipedia": "https://wikipedia.org/wiki/Hiroaki_Aoki"}, {"title": "Benihana", "wikipedia": "https://wikipedia.org/wiki/Benihana"}], "description": "Hiroaki Aoki, Japanese-American wrestler and businessman, founded Benihana (b. 1938)"}, {"year": "2008", "wikipedia": [{"title": "Mike Souchak", "wikipedia": "https://wikipedia.org/wiki/Mike_Souchak"}], "description": "Mike Souchak, American golfer (b. 1927)"}, {"year": "2011", "wikipedia": [{"title": "Pierrette Alarie", "wikipedia": "https://wikipedia.org/wiki/Pierrette_Alarie"}], "description": "Pierrette Alarie, Canadian soprano and educator (b. 1921)"}, {"year": "2011", "wikipedia": [{"title": "Roland Petit", "wikipedia": "https://wikipedia.org/wiki/Roland_Petit"}], "description": "Roland Petit, French dancer and choreographer (b. 1924)"}, {"year": "2012", "wikipedia": [{"title": "Dolphy", "wikipedia": "https://wikipedia.org/wiki/Dolphy"}], "description": "Dolphy, Filipino actor, singer, and producer (b. 1928)"}, {"year": "2012", "wikipedia": [{"title": "Peter Kyros", "wikipedia": "https://wikipedia.org/wiki/Peter_Kyros"}], "description": "Peter Kyros, American lawyer and politician (b. 1925)"}, {"year": "2012", "wikipedia": [{"title": "Berthe Meijer", "wikipedia": "https://wikipedia.org/wiki/Berthe_Meijer"}], "description": "Berthe Meijer, German-Dutch journalist and author (b. 1938)"}, {"year": "2012", "wikipedia": [{"title": "Fritz Langanke", "wikipedia": "https://wikipedia.org/wiki/Fritz_Langanke"}], "description": "Fritz Langanke, German lieutenant (b. 1919)"}, {"year": "2012", "wikipedia": [{"title": "Viktor Suslin", "wikipedia": "https://wikipedia.org/wiki/Viktor_Suslin"}], "description": "Viktor Suslin, Russian-German composer (b. 1942)"}, {"year": "2013", "wikipedia": [{"title": "Philip Caldwell", "wikipedia": "https://wikipedia.org/wiki/Philip_Caldwell"}], "description": "Philip Caldwell, American businessman (b. 1920)"}, {"year": "2013", "wikipedia": [{"title": "J\u00f3zef Gara", "wikipedia": "https://wikipedia.org/wiki/J%C3%B3zef_Gara"}], "description": "J\u00f3zef Gara, Polish poet and linguist (b. 1929)"}, {"year": "2013", "wikipedia": [{"title": "Concha Garc\u00eda Campoy", "wikipedia": "https://wikipedia.org/wiki/Concha_Garc%C3%ADa_Campoy"}], "description": "Concha Garc\u00eda Campoy, Spanish journalist (b. 1958)"}, {"year": "2013", "wikipedia": [{"title": "Caroline Duby Glassman", "wikipedia": "https://wikipedia.org/wiki/Caroline_Duby_Glassman"}], "description": "Caroline Duby Glassman, American lawyer and jurist (b. 1922)"}, {"year": "2013", "wikipedia": [{"title": "Ku Ok-hee", "wikipedia": "https://wikipedia.org/wiki/Ku_Ok-hee"}], "description": "Ku Ok-hee, South Korean golfer (b. 1956)"}, {"year": "2013", "wikipedia": [{"title": "Gokulananda Mahapatra", "wikipedia": "https://wikipedia.org/wiki/Gokulananda_Mahapatra"}], "description": "Gokulananda Mahapatra, Indian author and academic (b. 1922)"}, {"year": "2014", "wikipedia": [{"title": "Robert C. Broomfield", "wikipedia": "https://wikipedia.org/wiki/Robert_C._Broomfield"}], "description": "Robert C. Broomfield, American lawyer and judge (b. 1933)"}, {"year": "2014", "wikipedia": [{"title": "Juozas Kazickas", "wikipedia": "https://wikipedia.org/wiki/Juozas_Kazickas"}], "description": "Juozas Kazickas, Lithuanian-American businessman and philanthropist (b. 1918)"}, {"year": "2014", "wikipedia": [{"title": "Paul G. Risser", "wikipedia": "https://wikipedia.org/wiki/Paul_G._Risser"}], "description": "Paul G. Risser, American ecologist and academic (b. 1939)"}, {"year": "2014", "wikipedia": [{"title": "Zohra Sehgal", "wikipedia": "https://wikipedia.org/wiki/Zohra_Sehgal"}], "description": "Zohra Sehgal, Indian actress, dancer, and choreographer (b. 1912)"}, {"year": "2014", "wikipedia": [{"title": "Gloria Schweigerdt", "wikipedia": "https://wikipedia.org/wiki/Gloria_Schweigerdt"}], "description": "Gloria Schweigerdt, American baseball player (b. 1934)"}, {"year": "2015", "wikipedia": [{"title": "Roger Rees", "wikipedia": "https://wikipedia.org/wiki/Roger_Rees"}], "description": "Roger Rees, Welsh-American actor and director (b. 1944)"}, {"year": "2015", "wikipedia": [{"title": "Omar Sharif", "wikipedia": "https://wikipedia.org/wiki/Omar_Sharif"}], "description": "Omar Sharif, Egyptian actor (b. 1932)"}, {"year": "2015", "wikipedia": [{"title": "Jon Vickers", "wikipedia": "https://wikipedia.org/wiki/Jon_Vickers"}], "description": "Jon Vickers, Canadian tenor (b. 1926)"}, {"year": "2016", "wikipedia": [{"title": "Katharina Focke", "wikipedia": "https://wikipedia.org/wiki/Katharina_Focke"}], "description": "Katharina Focke, German politician (b. 1922)"}]}